README.md
setup.cfg
setup.py
aaransia/__init__.py
aaransia/alphabet.py
aaransia/defaults.py
aaransia/exceptions.py
aaransia/test.py
aaransia/text_samples.py
aaransia/transliteration.py
aaransia/utils.py
aaransia.egg-info/PKG-INFO
aaransia.egg-info/SOURCES.txt
aaransia.egg-info/dependency_links.txt
aaransia.egg-info/requires.txt
aaransia.egg-info/top_level.txt