Metadata-Version: 2.1
Name: aaransia
Version: 0.77
Summary: Languages and Dialects transliteration
Home-page: https://github.com/3aransia/3aransia
Author: Amine M. Boulouma
Author-email: amine@boulouma.com
License: Apache License 2.0
Download-URL: https://github.com/3aransia/3aransia/dist/aaransia-0.1.2.tar.gz
Keywords: python,nlp,language,moroccan,3aransia
Platform: UNKNOWN
Classifier: Development Status :: 3 - Alpha
Classifier: Intended Audience :: Developers
Classifier: Topic :: Software Development :: Build Tools
Classifier: License :: OSI Approved :: Apache Software License
Classifier: Programming Language :: Python :: 3
Classifier: Programming Language :: Python :: 3.4
Classifier: Programming Language :: Python :: 3.5
Classifier: Programming Language :: Python :: 3.6
Classifier: Programming Language :: Python :: 3.7
